faa_aircraft_registry/__init__.py
faa_aircraft_registry/aircraft.py
faa_aircraft_registry/engines.py
faa_aircraft_registry/master.py
faa_aircraft_registry/read_registry.py
faa_aircraft_registry/types.py
faa_aircraft_registry/utils.py
tests/__init__.py
tests/test_certification.py
faa_aircraft_registry-0.1.0.dist-info/LICENSE
faa_aircraft_registry-0.1.0.dist-info/METADATA
faa_aircraft_registry-0.1.0.dist-info/WHEEL
faa_aircraft_registry-0.1.0.dist-info/top_level.txt
faa_aircraft_registry-0.1.0.dist-info/RECORD
