Metadata-Version: 2.1
Name: faa-aircraft-registry
Version: 0.1.0
Summary: Format FAA aircraft registry database into Python dictionaries for programmatic use.
Home-page: https://github.com/ClearAerospace/faa-aircraft-registry
Author: Austin Baldwin
Author-email: austin.baldwin@clearaerospace.com
License: MIT
Keywords: faa aircraft registry
Platform: UNKNOWN
Classifier: Programming Language :: Python :: 3
Classifier: License :: OSI Approved :: MIT License
Classifier: Operating System :: OS Independent
Classifier: Development Status :: 3 - Alpha
Classifier: Natural Language :: English
Requires-Python: >=3.8
